ttyd_cli/__init__.py
ttyd_cli/__main__.py
ttyd_cli/auth.py
ttyd_cli/cli.py
ttyd_cli/client.py
ttyd_cli/exceptions.py
ttyd_cli/main.py
ttyd_cli/utils.py
ttyd_cli/platforms/__init__.py
ttyd_cli/platforms/base.py
ttyd_cli/platforms/unix.py
ttyd_cli/platforms/windows.py
ttyd_client-0.1.4.dist-info/METADATA
ttyd_client-0.1.4.dist-info/WHEEL
ttyd_client-0.1.4.dist-info/entry_points.txt
ttyd_client-0.1.4.dist-info/top_level.txt
ttyd_client-0.1.4.dist-info/RECORD
