Metadata-Version: 2.4
Name: ttyd-client
Version: 0.1.4
Summary: A Python client library for connecting to TTYD (tty over WebSocket) servers with full terminal support, authentication, and cross-platform compatibility
Requires-Python: >=3.12
Requires-Dist: requests>=2.32.5
Requires-Dist: websocket-client>=1.9.0
Provides-Extra: dev
Requires-Dist: pytest>=7.4.0; extra == "dev"
Requires-Dist: pytest-cov>=4.1.0; extra == "dev"
Requires-Dist: pytest-mock>=3.11.0; extra == "dev"
Requires-Dist: ruff>=0.1.0; extra == "dev"
